[{"Code": "AF", "Name": "Afghanistan"}, {"Code": "AX", "Name": "\ u00c5land Islands"}, {"Code": "AL", "Name ":" Albanie "}, {" Code ":" DZ "," Name ":" Algérie "}, {" Code ":" AS "," Name ":" American Samoa "}, {" Code ":" AD "," Name ":" Andorra "}, {" Code ":" AO "," Name ":" Angola "}, {" Code ":" AI "," Name ":" Anguilla "}, {" Code ":" AQ "," Name ":" Antarctica "}, {" Code ":" AG "," Name ":" Antigua-et-Barbuda "}, {" Code ":" AR "," Name ":" Argentine "}, {" Code ":" AM "," Name ":" Armenia "}, {" Code ":" AW "," Name ":" Aruba "}, {" Code ":" AU "," Nom ":" Australie "}, {" Code ":" AT "," Nom ":" Autriche "}, {" Code ":" AZ "," Nom ":" Azerbaïdjan "}, {" Code ":" BS "," Name ":" Bahamas "}, {" Code ":" BH "," Name ":" Bahreïn "}, {" Code ":" BD "," Name ":" Bangladesh "}, {" Code ":" BB "," Name ":" Barbados "}, {" Code ":" BY "," Name ":" Belarus "}, {" Code ":" BE "," Name ":" Belgium " }, {"Code": "BZ", "Name": "Belize"}, {"Code": "BJ", "Name": "Benin"}, {"Code": "BM", "Name" : "Bermudes"}, {"Code": "BT", "Name": "Bhoutan"}, {"Code": "BO", "Name": "Bolivie, État plurinational de"}, {"Code" : "BQ", "Name": "Bonaire, Sint Eustatius and Saba"}, {"Code": "BA", "Name": "Bosnie-Herzégovine"}, {"Code": "BW", "Name": "Botswana" }, {"Code": "BV", "Name": "Bouvet Island"}, {"Code": "BR", "Name": "Brazil"}, {"Code": "IO", "Name ":" Territoire britannique de l'océan Indien "}, {" Code ":" BN "," Name ":" Brunei Darussalam "}, {" Code ":" BG "," Name ":" Bulgaria "}, {" Code ":" BF "," Name ":" Burkina Faso "}, {" Code ":" BI "," Name ":" Burundi "}, {" Code ":" KH "," Name ":" Cambodge " }, {"Code": "CM", "Name": "Cameroun"}, {"Code": "CA", "Name": "Canada"}, {"Code": "CV", "Name" : "Cape Verde"}, {"Code": "KY", "Name": "Cayman Islands"}, {"Code": "CF", "Name": "Central African Republic"}, {"Code" : "TD", "Name": "Chad"}, {"Code": "CL", "Name": "Chile"}, {"Code": "CN", "Name": "China"}, {"Code": "CX", "Name": "Christmas Island"}, {"Code": "CC", "Name": "Cocos (Keeling) Islands"}, {"Code": "CO", "Name": "Colombia"}, {"Code": "KM", "Name": "Comoros"}, {"Code": "CG", "Name": "Congo"}, {"Code": "CD", "Name": "Congo, the Democratic Republic of the"}, {"Cod e ":" CK "," Name ":" Cook Islands "}, {" Code ":" CR "," Name ":" Costa Rica "}, {" Code ":" CI "," Name ":" C \ u00f4te d'Ivoire "}, {" Code ":" HR "," Name ":" Croatia "}, {" Code ":" CU "," Name ":" Cuba "}, {" Code ": "CW", "Name": "Cura \ u00e7ao"}, {"Code": "CY", "Name": "Cyprus"}, {"Code": "CZ", "Name": "Czech Republic" }, {"Code": "DK", "Name": "Denmark"}, {"Code": "DJ", "Name": "Djibouti"}, {"Code": "DM", "Name" : "Dominique"}, {"Code": "DO", "Name": "République dominicaine"}, {"Code": "EC", "Name": "Equateur"}, {"Code": "EG "," Name ":" Egypt "}, {" Code ":" SV "," Name ":" El Salvador "}, {" Code ":" GQ "," Name ":" Equatorial Guinea "}, { "Code": "ER", "Name": "Eritrea"}, {"Code": "EE", "Name": "Estonie"}, {"Code": "ET", "Name": "Ethiopie "}, {" Code ":" FK "," Name ":" Falkland Islands (Malvinas) "}, {" Code ":" FO "," Name ":" Faroe Islands "}, {" Code ":" FJ "," Name ":" Fidji "}, {" Code ":" FI "," Name ":" Finland "}, {" Code ":" FR "," Name ":" France "}, {" Code ":" GF "," Name ":" French Guiana "}, {" Code ":" PF "," Name ":" French Polynesia "}, {" Code ":" TF "," Name ":" Français Territoires du Sud "}, {" Code ":" GA "," Name ":" Gabon "}, {" Code ":" GM "," Name ":" Gambia "}, {" Code ":" GE ", "Name": "Georgia"}, {"Code": "DE", "Name": "Germany"}, {"Code": "GH", "Name": "Ghana"}, {"Code": "GI", "Name": "Gibraltar"}, {"Code": "GR", "Name": "Greece"}, {"Code": "GL", "Name": "Groenland"}, { "Code": "GD", "Name": "Grenada"}, {"Code": "GP", "Name": "Guadeloupe"}, {"Code": "GU", "Name": "Guam "}, {" Code ":" GT "," Name ":" Guatemala "}, {" Code ":" GG "," Name ":" Guernsey "}, {" Code ":" GN "," Name ":" Guinée "}, {" Code ":" GW "," Name ":" Guinée-Bissau "}, {" Code ":" GY "," Name ":" Guyana "}, {" Code ": "HT", "Name": "Haïti"}, {"Code": "HM", "Name": "Heard Island and McDonald Islands"}, {"Code": "VA", "Name": "Holy Voir (État de la Cité du Vatican) "}, {" Code ":" HN "," Name ":" Honduras "}, {" Code ":" HK "," Name ":" Hong Kong "}, {" Code " : "HU", "Name": "Hungary"}, {"Code": "IS", "Name": "Iceland"}, {"Code": "IN", "Name": "India"}, {"Code": "ID", "Name": "Indonesia"}, {"Code": "IR", "Name": "Iran, Islamic Republic of"}, {"Code": "IQ", " Nom" : "Iraq"}, {"Code": "IE", "Name": "Ireland"}, {"Code": "IM", "Name": "Isle of Man"}, {"Code": " IL "," Name ":" Israel "}, {" Code ":" IT "," Name ":" Italy "}, {" Code ":" JM "," Name ":" Jamaica "}, {" Code ":" JP "," Name ":" Japan "}, {" Code ":" JE "," Name ":" Jersey "}, {" Code ":" JO "," Name ":" Jordan " }, {"Code": "KZ", "Name": "Kazakhstan"}, {"Code": "KE", "Name": "Kenya"}, {"Code": "KI", "Name" : "Kiribati"}, {"Code": "KP", "Name": "Corée, République populaire démocratique de"}, {"Code": "KR", "Name": "Corée, République de"}, {"Code": "KW", "Name": "Kuwait"}, {"Code": "KG", "Name": "Kyrgyzstan"}, {"Code": "LA", "Name": " République démocratique populaire lao "}, {" Code ":" LV "," Name ":" Latvia "}, {" Code ":" LB "," Name ":" Lebanon "}, {" Code ":" LS "," Name ":" Lesotho "}, {" Code ":" LR "," Name ":" Liberia "}, {" Code ":" LY "," Name ":" Libya "}, {" Code ":" LI "," Name ":" Liechtenstein "}, {" Code ":" LT "," Name ":" Lithuania "}, {" Code ":" LU "," Name ":" Luxembourg "} , {"Code": "MO", "Name": "Macao"}, {"Code": "MK", ​​"Name": "Macédoine, ancienne République yougoslave de
